fast/__init__.py
fast/atomic_structure.py
fast/config.py
fast/electric_field.py
fast/error_propagation.py
fast/evolution.py
fast/graphic.py
fast/misc.py
fast/rk4.py
fast/stationary.py
fast/symbolic.py
fast_atomic-1.1.2.dist-info/DESCRIPTION.rst
fast_atomic-1.1.2.dist-info/METADATA
fast_atomic-1.1.2.dist-info/RECORD
fast_atomic-1.1.2.dist-info/WHEEL
fast_atomic-1.1.2.dist-info/metadata.json
fast_atomic-1.1.2.dist-info/top_level.txt
