Metadata-Version: 2.0
Name: fast-atomic
Version: 1.1.2
Summary: FAST is an acronym for FAST Atomic Spectroscopy from Theory.
Home-page: https://github.com/oscarlazoarjona/fast
Author: Oscar Gerardo Lazo Arjona
Author-email: oscar.lazo@correo.nucleares.unam.mx
License: License :: OSI Approved :: GNU General Public License v3 (GPLv3)
Keywords: atomic-physics
Platform: UNKNOWN
Classifier: Development Status :: 4 - Beta
Classifier: Intended Audience :: Science/Research
Classifier: Topic :: Scientific/Engineering :: Physics
Classifier: License :: OSI Approved :: GNU General Public License v3 (GPLv3)
Classifier: Programming Language :: Python :: 2.7
Classifier: Operating System :: POSIX :: Linux
